blaziken/__init__.py
blaziken/api.py
blaziken/constants.py
blaziken/enums.py
blaziken/exceptions.py
blaziken/http.py
blaziken/meta.py
blaziken/models.py
blaziken/utils.py
blaziken-2020.10.21.1.dist-info/METADATA
blaziken-2020.10.21.1.dist-info/WHEEL
blaziken-2020.10.21.1.dist-info/license.txt
blaziken-2020.10.21.1.dist-info/top_level.txt
blaziken-2020.10.21.1.dist-info/RECORD
