Metadata-Version: 2.1
Name: blaziken
Version: 2020.10.21.1
Summary: An object-oriented implementation of the Backblaze B2 API
Home-page: https://github.com/vgjournal/blaziken
Author: dreiq
Author-email: admin@vgjounal.net
License: UNKNOWN
Platform: UNKNOWN
Classifier: Development Status :: 4 - Beta
Classifier: Intended Audience :: Developers
Classifier: License :: OSI Approved :: MIT License
Classifier: Operating System :: OS Independent
Classifier: Programming Language :: Python :: 3
Classifier: Topic :: Internet :: WWW/HTTP
Classifier: Typing :: Typed
Requires-Python: >=3.7
Requires-Dist: requests
